tlhengine/__init__.py
tlhengine/dataset.py
tlhengine/engine.py
tlhengine/fix.py
tlhengine/loss.py
tlhengine/models1.py
tlhengine/resnetv1_b.py
tlhengine/scores.py
tlhengine/segbase.py
tlhengine/tfmodels.py
tlhengine/utils.py
tlhengine/version.py
tlhengine/zhihu_deeplab.py
tlhengine/datasets/__init__.py
tlhengine/datasets/segbase.py
tlhengine/datasets/voc.py
tlhengine/models/__init__.py
tlhengine/models/beit.py
tlhengine/models/deploy.py
tlhengine/models/protonet.py
tlhengine/models/resnet_v2.py
tlhengine/models/utils.py
tlhengine/models/vision_transformer.py
tlhengine/models/vit_google.py
tlhengine/models/clip/__init__.py
tlhengine/models/clip/bpe_simple_vocab_16e6.txt.gz
tlhengine/models/clip/clip.py
tlhengine/models/clip/model.py
tlhengine/models/clip/simple_tokenizer.py
tlhengine-2.0.3.dist-info/METADATA
tlhengine-2.0.3.dist-info/WHEEL
tlhengine-2.0.3.dist-info/RECORD
