Metadata-Version: 2.4
Name: tlhengine
Version: 2.0.3
Summary: tlh engine
Project-URL: Homepage, https://gitee.com/tianlianghai/tlh_engine
Project-URL: Issues, https://gitee.com/tianlianghai/tlh_engine/issues
Author-email: lianghai tian <tianlh@163.com>
License-Expression: MIT
Classifier: Operating System :: OS Independent
Classifier: Programming Language :: Python :: 3
Requires-Python: >=3.8
Requires-Dist: nvidia-ml-py
